flowtimer/__init__.py
flowtimer/cli.py
flowtimer/config.py
flowtimer/timer.py
flowtimer/utils.py
flowtimer-0.1.0.dist-info/LICENSE
flowtimer-0.1.0.dist-info/METADATA
flowtimer-0.1.0.dist-info/WHEEL
flowtimer-0.1.0.dist-info/entry_points.txt
flowtimer-0.1.0.dist-info/top_level.txt
flowtimer-0.1.0.dist-info/RECORD
