Metadata-Version: 2.1
Name: flowtimer
Version: 0.1.0
Summary: A terminal Pomodoro timer with productivity stats
Home-page: https://github.com/luhuadong/flowtimer
Author: luhuadong
Author-email: luhuadong@163.com
License: MIT
License-File: LICENSE
Requires-Dist: click>=8.0
Requires-Dist: rich>=13.0
Requires-Dist: plotext>=5.0
Requires-Dist: python-dotenv>=0.19
Requires-Dist: simpleaudio>=1.0.4; sys_platform == "linux"
